{
    "data": [
        { "year_of_experience": "0-5", "amount": 50, "combinations": ["CV Review"] },
        { "year_of_experience": "0-5", "amount": 50, "combinations": ["LinkedIn Optimisation"] },
        { "year_of_experience": "0-5", "amount": 50, "combinations": ["Cover Letter"] },
        { "year_of_experience": "0-5", "amount": 100, "combinations": ["Biography/Portfolio"] },

        { "year_of_experience": "0-5", "amount": 70, "combinations": ["CV Review", "LinkedIn Optimisation"] },
        { "year_of_experience": "0-5", "amount": 70, "combinations": ["CV Review", "Cover Letter"] },
        { "year_of_experience": "0-5", "amount": 150, "combinations": ["CV Review", "Biography/Portfolio"] },
        { "year_of_experience": "0-5", "amount": 70, "combinations": ["LinkedIn Optimisation", "Cover Letter"] },
        { "year_of_experience": "0-5", "amount": 150, "combinations": ["LinkedIn Optimisation", "Biography/Portfolio"] },
        { "year_of_experience": "0-5", "amount": 150, "combinations": ["Cover Letter", "Biography/Portfolio"] },

        { "year_of_experience": "0-5", "amount": 100, "combinations": ["CV Review", "LinkedIn Optimisation", "Cover Letter"] },
        { "year_of_experience": "0-5", "amount": 200, "combinations": ["CV Review", "LinkedIn Optimisation", "Biography/Portfolio"] },
        { "year_of_experience": "0-5", "amount": 200, "combinations": ["CV Review", "Cover Letter", "Biography/Portfolio"] },
        { "year_of_experience": "0-5", "amount": 200, "combinations": ["LinkedIn Optimisation", "Cover Letter", "Biography/Portfolio"] },
        { "year_of_experience": "0-5", "amount": 250, "combinations": ["CV Review", "LinkedIn Optimisation", "Cover Letter", "Biography/Portfolio"] },

        { "year_of_experience": "6-10", "amount": 70, "combinations": ["CV Review"] },
        { "year_of_experience": "6-10", "amount": 70, "combinations": ["LinkedIn Optimisation"] },
        { "year_of_experience": "6-10", "amount": 70, "combinations": ["Cover Letter"] },
        { "year_of_experience": "6-10", "amount": 150, "combinations": ["Biography/Portfolio"] },

        { "year_of_experience": "6-10", "amount": 135, "combinations": ["CV Review", "LinkedIn Optimisation"] },
        { "year_of_experience": "6-10", "amount": 135, "combinations": ["CV Review", "Cover Letter"] },
        { "year_of_experience": "6-10", "amount": 230, "combinations": ["CV Review", "Biography/Portfolio"] },
        { "year_of_experience": "6-10", "amount": 135, "combinations": ["LinkedIn Optimisation", "Cover Letter"] },
        { "year_of_experience": "6-10", "amount": 230, "combinations": ["LinkedIn Optimisation", "Biography/Portfolio"] },
        { "year_of_experience": "6-10", "amount": 230, "combinations": ["Cover Letter", "Biography/Portfolio"] },

        { "year_of_experience": "6-10", "amount": 200, "combinations": ["CV Review", "LinkedIn Optimisation", "Cover Letter"] },
        { "year_of_experience": "6-10", "amount": 280, "combinations": ["CV Review", "LinkedIn Optimisation", "Biography/Portfolio"] },
        { "year_of_experience": "6-10", "amount": 280, "combinations": ["CV Review", "Cover Letter", "Biography/Portfolio"] },
        { "year_of_experience": "6-10", "amount": 280, "combinations": ["LinkedIn Optimisation", "Cover Letter", "Biography/Portfolio"] },
        { "year_of_experience": "6-10", "amount": 350, "combinations": ["CV Review", "LinkedIn Optimisation", "Cover Letter", "Biography/Portfolio"] },

        { "year_of_experience": "11-15", "amount": 120, "combinations": ["CV Review"] },
        { "year_of_experience": "11-15", "amount": 120, "combinations": ["LinkedIn Optimisation"] },
        { "year_of_experience": "11-15", "amount": 120, "combinations": ["Cover Letter"] },
        { "year_of_experience": "11-15", "amount": 200, "combinations": ["Biography/Portfolio"] },

        { "year_of_experience": "11-15", "amount": 200, "combinations": ["CV Review", "LinkedIn Optimisation"] },
        { "year_of_experience": "11-15", "amount": 200, "combinations": ["CV Review", "Cover Letter"] },
        { "year_of_experience": "11-15", "amount": 300, "combinations": ["CV Review", "Biography/Portfolio"] },
        { "year_of_experience": "11-15", "amount": 200, "combinations": ["LinkedIn Optimisation", "Cover Letter"] },
        { "year_of_experience": "11-15", "amount": 300, "combinations": ["LinkedIn Optimisation", "Biography/Portfolio"] },
        { "year_of_experience": "11-15", "amount": 300, "combinations": ["Cover Letter", "Biography/Portfolio"] },

        { "year_of_experience": "11-15", "amount": 300, "combinations": ["CV Review", "LinkedIn Optimisation", "Cover Letter"] },
        { "year_of_experience": "11-15", "amount": 400, "combinations": ["CV Review", "LinkedIn Optimisation", "Biography/Portfolio"] },
        { "year_of_experience": "11-15", "amount": 400, "combinations": ["CV Review", "Cover Letter", "Biography/Portfolio"] },
        { "year_of_experience": "11-15", "amount": 400, "combinations": ["LinkedIn Optimisation", "Cover Letter", "Biography/Portfolio"] },
        { "year_of_experience": "11-15", "amount": 500, "combinations": ["CV Review", "LinkedIn Optimisation", "Cover Letter", "Biography/Portfolio"] },

        { "year_of_experience": "15+", "amount": 160, "combinations": ["CV Review"] },
        { "year_of_experience": "15+", "amount": 160, "combinations": ["LinkedIn Optimisation"] },
        { "year_of_experience": "15+", "amount": 160, "combinations": ["Cover Letter"] },
        { "year_of_experience": "15+", "amount": 400, "combinations": ["Biography/Portfolio"] },

        { "year_of_experience": "15+", "amount": 300, "combinations": ["CV Review", "LinkedIn Optimisation"] },
        { "year_of_experience": "15+", "amount": 300, "combinations": ["CV Review", "Cover Letter"] },
        { "year_of_experience": "15+", "amount": 500, "combinations": ["CV Review", "Biography/Portfolio"] },
        { "year_of_experience": "15+", "amount": 300, "combinations": ["LinkedIn Optimisation", "Cover Letter"] },
        { "year_of_experience": "15+", "amount": 500, "combinations": ["LinkedIn Optimisation", "Biography/Portfolio"] },
        { "year_of_experience": "15+", "amount": 500, "combinations": ["Cover Letter", "Biography/Portfolio"] },

        { "year_of_experience": "15+", "amount": 450, "combinations": ["CV Review", "LinkedIn Optimisation", "Cover Letter"] },
        { "year_of_experience": "15+", "amount": 650, "combinations": ["CV Review", "LinkedIn Optimisation", "Biography/Portfolio"] },
        { "year_of_experience": "15+", "amount": 650, "combinations": ["CV Review", "Cover Letter", "Biography/Portfolio"] },
        { "year_of_experience": "15+", "amount": 650, "combinations": ["LinkedIn Optimisation", "Cover Letter", "Biography/Portfolio"] },
        { "year_of_experience": "15+", "amount": 800, "combinations": ["CV Review", "LinkedIn Optimisation", "Cover Letter", "Biography/Portfolio"] }
    ]
}
